maxllm/__init__.py
maxllm/maxllm.py
maxllm-0.1.0.dist-info/licenses/LICENSE
maxllm-0.1.0.dist-info/METADATA
maxllm-0.1.0.dist-info/WHEEL
maxllm-0.1.0.dist-info/top_level.txt
maxllm-0.1.0.dist-info/RECORD
