Metadata-Version: 2.4
Name: maxllm
Version: 0.1.0
Summary: A unified OpenAI API client with rate limiting, caching, and batch processing
Author-email: Your Name <your.email@example.com>
License: MIT
Project-URL: Homepage, https://github.com/yourusername/maxllm
Project-URL: Repository, https://github.com/yourusername/maxllm
Project-URL: Issues, https://github.com/yourusername/maxllm/issues
Classifier: Development Status :: 3 - Alpha
Classifier: Intended Audience :: Developers
Classifier: License :: OSI Approved :: MIT License
Classifier: Programming Language :: Python :: 3
Classifier: Programming Language :: Python :: 3.8
Classifier: Programming Language :: Python :: 3.9
Classifier: Programming Language :: Python :: 3.10
Classifier: Programming Language :: Python :: 3.11
Classifier: Programming Language :: Python :: 3.12
Requires-Python: >=3.8
License-File: LICENSE
Requires-Dist: tqdm>=4.65.0
Requires-Dist: tiktoken>=0.5.0
Requires-Dist: pydantic>=2.0.0
Requires-Dist: openai>=1.0.0
Requires-Dist: pyyaml>=6.0
Requires-Dist: requests>=2.28.0
Requires-Dist: aiolimiter>=1.1.0
Requires-Dist: diskcache>=5.6.0
Requires-Dist: json5>=0.9.0
Requires-Dist: json-repair>=0.7.0
Requires-Dist: python-dotenv>=1.0.0
Provides-Extra: transformers
Requires-Dist: transformers>=4.30.0; extra == "transformers"
Dynamic: license-file
